tradehub/__init__.py
tradehub/authenticated_client.py
tradehub/decentralized_client.py
tradehub/demex_client.py
tradehub/public_account_client.py
tradehub/public_blockchain_client.py
tradehub/transactions.py
tradehub/types.py
tradehub/utils.py
tradehub/wallet.py
tradehub/websocket_client.py
tradehub-2.0.1.dist-info/LICENSE
tradehub-2.0.1.dist-info/WHEEL
tradehub-2.0.1.dist-info/METADATA
tradehub-2.0.1.dist-info/RECORD
