Metadata-Version: 2.1
Name: tradehub
Version: 2.0.1
Summary: Python Client to interact with the Switcheo Tradehub Blockchain to manage staking, liquidity pools, governance, and trading on Demex.
Home-page: https://github.com/Mai-Te-Pora/tradehub-python
License: MIT
Author: Your Name
Author-email: you@example.com
Requires-Python: >=3.8,<4.0
Classifier: License :: OSI Approved :: MIT License
Classifier: Programming Language :: Python :: 3
Classifier: Programming Language :: Python :: 3.8
Classifier: Programming Language :: Python :: 3.9
Requires-Dist: base58 (>=2.1.0,<3.0.0)
Requires-Dist: bech32 (>=1.2.0,<2.0.0)
Requires-Dist: ecdsa (>=0.16.1,<0.17.0)
Requires-Dist: hdwallets (>=0.1.2,<0.2.0)
Requires-Dist: jsons (>=1.3.1,<2.0.0)
Requires-Dist: mnemonic (>=0.19,<0.20)
Requires-Dist: requests (>=2.25.1,<3.0.0)
Requires-Dist: web3 (>=5.15.0,<6.0.0)
Project-URL: Documentation, https://mai-te-pora.github.io/tradehub-python/
Project-URL: Repository, https://github.com/Mai-Te-Pora/tradehub-python
